baron/__init__.py
baron/baron.py
baron/dumper.py
baron/formatting_grouper.py
baron/future.py
baron/grammator.py
baron/grammator_control_structures.py
baron/grammator_data_structures.py
baron/grammator_imports.py
baron/grammator_operators.py
baron/grammator_primitives.py
baron/grouper.py
baron/helpers.py
baron/indentation_marker.py
baron/inner_formatting_grouper.py
baron/parser.py
baron/path.py
baron/render.py
baron/spliter.py
baron/token.py
baron/tokenizer.py
baron/utils.py
baron-0.10.1.dist-info/LICENSE
baron-0.10.1.dist-info/METADATA
baron-0.10.1.dist-info/WHEEL
baron-0.10.1.dist-info/top_level.txt
baron-0.10.1.dist-info/RECORD
