Metadata-Version: 2.1
Name: baron
Version: 0.10.1
Summary: Full Syntax Tree for python to make writing refactoring code a realist task
Home-page: https://github.com/PyCQA/baron
Author: Laurent Peuch
Author-email: cortex@worlddomination.be
License: lgplv3+
Keywords: ast fst refactoring syntax tree
Platform: UNKNOWN
Classifier: Development Status :: 3 - Alpha
Classifier: Intended Audience :: Developers
Classifier: Programming Language :: Python :: 2
Classifier: Programming Language :: Python :: 2.7
Classifier: Programming Language :: Python :: 3
Classifier: Programming Language :: Python :: 3.2
Classifier: Programming Language :: Python :: 3.3
Classifier: License :: OSI Approved :: GNU Lesser General Public License v3 (LGPLv3)
Classifier: Topic :: Software Development
Classifier: Topic :: Software Development :: Code Generators
Classifier: Topic :: Software Development :: Libraries
License-File: LICENSE
